ursina_proteins/__init__.py
ursina_proteins/atoms.py
ursina_proteins/chains.py
ursina_proteins/protein.py
ursina_proteins-2.0.0.dist-info/METADATA
ursina_proteins-2.0.0.dist-info/WHEEL
ursina_proteins-2.0.0.dist-info/licenses/LICENSE
ursina_proteins-2.0.0.dist-info/RECORD
