Metadata-Version: 2.4
Name: ursina-proteins
Version: 2.0.0
Summary: A Python package for rendering protein structures of PDB format in 3D using Ursina
Project-URL: Homepage, https://github.com/HarrisonTCodes/ursina-proteins
Project-URL: Source, https://github.com/HarrisonTCodes/ursina-proteins
Author: HarrisonTCodes
License: MIT License
License-File: LICENSE
Requires-Python: <3.14,>=3.12
Requires-Dist: biopython<2.0,>=1.85
Requires-Dist: scipy<2.0.0,>=1.15.2
Requires-Dist: ursina<9.0.0,>=7.0.0
